README.rst
setup.cfg
setup.py
greb/__init__.py
greb/meaning.py
greb/opts.py
greb.egg-info/PKG-INFO
greb.egg-info/SOURCES.txt
greb.egg-info/dependency_links.txt
greb.egg-info/entry_points.txt
greb.egg-info/requires.txt
greb.egg-info/top_level.txt
test/test_greb.py