Metadata-Version: 1.1
Name: greb
Version: 0.0.8
Summary: Finds the meaning for a particular word. Lists suggestion in case accurate word is not found.
Home-page: https://github.com/staranjeet/greb
Author: Taranjeet Singh
Author-email: reachtotj@gmail.com
License: MIT
Keywords: dictionary cli,word meaning,meaning-cli
Platform: UNKNOWN
Classifier: Development Status :: 3 - Alpha
Classifier: Environment :: Console
Classifier: Intended Audience :: Developers
Classifier: Intended Audience :: Information Technology
Classifier: Natural Language :: English
Classifier: Topic :: Software Development :: Build Tools
Classifier: License :: OSI Approved :: MIT License
Classifier: Programming Language :: Python :: 2
Classifier: Programming Language :: Python :: 2.6
Classifier: Programming Language :: Python :: 2.7
Classifier: Programming Language :: Python :: 3
Classifier: Programming Language :: Python :: 3.0
Classifier: Programming Language :: Python :: 3.1
Classifier: Programming Language :: Python :: 3.2
Classifier: Programming Language :: Python :: 3.3
Classifier: Programming Language :: Python :: 3.4
